libero2gym/__init__.py
libero2gym/libero_env.py
libero2gym/vector_env.py
libero2gym-0.1.0.dist-info/METADATA
libero2gym-0.1.0.dist-info/WHEEL
libero2gym-0.1.0.dist-info/top_level.txt
libero2gym-0.1.0.dist-info/RECORD
