Metadata-Version: 2.4
Name: libero2gym
Version: 0.1.0
Summary: A Gym wrapper for LIBERO robotics task suites.
Author-email: Zibin Dong <zibindong@outlook.com>
Classifier: Programming Language :: Python :: 3
Classifier: License :: OSI Approved :: MIT License
Classifier: Operating System :: OS Independent
Requires-Python: >=3.8
Requires-Dist: numpy
Requires-Dist: gym
Requires-Dist: robosuite
Requires-Dist: termcolor
Provides-Extra: pc
Requires-Dist: torch; extra == "pc"
Requires-Dist: open3d; extra == "pc"
Requires-Dist: pytorch3d; extra == "pc"
